{
  "date" : "01-12-2026",
  "day" : {
    "en" : "Tuesday",
    "ta" : "செவ்வாய்"
  },
  "tamil_month" : {
    "en" : "Karthigai",
    "ta" : "கார்த்திகை"
  },
  "tamil_date" : "15",
  "tamil_year" : {
    "en" : "Parabava",
    "ta" : "பராபவ"
  },
  "islamic_date" : {
    "en" : "Jamad ul Akhir 21",
    "ta" : "ஜமாதுல் ஆகிர் 21"
  },
  "paksha" : {
    "en" : "Krishna Paksham",
    "ta" : "கிருஷ்ண பட்சம்"
  },
  "panchangam" : {
    "tithi" : {
      "en" : "Ashtami 55.50 (04.35) ends, then Navami",
      "ta" : "அஷ்டமி 55.50 (கா. 04.35) மகம் 21.35 (மா. 02.53)"
    },
    "nakshatra" : {
      "en" : "Magam 21.35 (02.53) ends, then Pooram",
      "ta" : "மகம் 21.35 (மா. 02.53)"
    },
    "lagnam" : {
      "en" : "Viruchiga Lagnam, Duration Na. 2 Vi. 43",
      "ta" : "விருச்சிக லக்னம் இருப்பு நா. 2 வி. 43"
    },
    "karanam" : {
      "en" : "7.30 - 9",
      "ta" : "7.30-9"
    }
  },
  "timings" : {
    "sunrise" : {
      "en" : "6.15",
      "ta" : "6.15"
    }
  },
  "auspicious_times" : {
    "morning" : {
      "en" : "7.45 - 8.45",
      "ta" : "7.45-8.45"
    },
    "evening" : {
      "en" : "4.45 - 5.45",
      "ta" : "4.45-5.45"
    }
  },
  "gowri_nalla_neram" : {
    "morning" : {
      "en" : "10.45 - 11.45",
      "ta" : "10.45-11.45"
    },
    "evening" : {
      "en" : "7.30 - 8.30",
      "ta" : "7.30-8.30"
    }
  },
  "inauspicious_times" : {
    "rahu" : {
      "morning" : "03.00",
      "evening" : "04.30"
    },
    "gulikai" : {
      "morning" : "12.00",
      "evening" : "01.30"
    },
    "emagandam" : {
      "morning" : "09.00",
      "evening" : "10.30"
    }
  },
  "soolam" : {
    "en" : "North",
    "ta" : "வடக்கு"
  },
  "pariharam" : {
    "en" : "Paal",
    "ta" : "பால்"
  },
  "chandrashtamam" : {
    "en" : "Thiruvonam, Avittam",
    "ta" : "திருவோணம், அவிட்டம்"
  }
}