{
  "date" : "21-07-2026",
  "day" : {
    "en" : "Tuesday",
    "ta" : "செவ்வாய்"
  },
  "tamil_month" : {
    "en" : "Aadi",
    "ta" : "ஆடி"
  },
  "tamil_date" : "5",
  "tamil_year" : {
    "en" : "Parabava",
    "ta" : "பராபவ"
  },
  "islamic_date" : {
    "en" : "6",
    "ta" : "6"
  },
  "paksha" : {
    "en" : "Shukla Paksham",
    "ta" : "சுக்ல பட்சம்"
  },
  "panchangam" : {
    "tithi" : {
      "en" : "Saptami up to 08.41, then Ashtami",
      "ta" : "சப்தமி கா.08.41 வரை, பின்பு அஷ்டமி"
    },
    "nakshatra" : {
      "en" : "Hastham up to 12.07, then Chithirai",
      "ta" : "ஹஸ்தம் கா.12.07 வரை, பின்பு சித்திரை"
    },
    "lagnam" : {
      "en" : "Irruppu Na. 4 Vi. 48",
      "ta" : "இருப்பு நா. 4 வி. 48"
    },
    "karanam" : {
      "en" : "7.30-9",
      "ta" : "7.30-9"
    }
  },
  "timings" : {
    "sunrise" : {
      "en" : "6.01",
      "ta" : "6.01"
    }
  },
  "auspicious_times" : {
    "morning" : {
      "en" : "10.45-11.45",
      "ta" : "10.45-11.45"
    },
    "evening" : {
      "en" : "4.45-5.45",
      "ta" : "4.45-5.45"
    }
  },
  "gowri_nalla_neram" : {
    "morning" : {
      "en" : "1.45-2.45",
      "ta" : "1.45-2.45"
    },
    "evening" : {
      "en" : "7.30-8.30",
      "ta" : "7.30-8.30"
    }
  },
  "inauspicious_times" : {
    "rahu" : {
      "morning" : "03.00",
      "evening" : "04.30"
    },
    "gulikai" : {
      "morning" : "12.00",
      "evening" : "01.30"
    },
    "emagandam" : {
      "morning" : "09.00",
      "evening" : "10.30"
    }
  },
  "soolam" : {
    "en" : "Vadaku (North)",
    "ta" : "வடக்கு"
  },
  "pariharam" : {
    "en" : "Paal",
    "ta" : "பால்"
  },
  "chandrashtamam" : {
    "en" : "Chandra Ashtamam",
    "ta" : "சந்திராஷ்டமம்"
  }
}